flatmake/__init__.py
flatmake/__main__.py
flatmake/cli.py
flatmake/flatmake.py
flatmake/py.typed
flatmake/idl/make.sh
flatmake/idl/python/Dim/ColorArray1D.py
flatmake/idl/python/Dim/Coordinates2D.py
flatmake/idl/python/Dim/Dim.py
flatmake/idl/python/Dim/Float32bArray.py
flatmake/idl/python/Dim/LabeledIndexSet.py
flatmake/idl/python/Dim/LabeledIndexSuperSet.py
flatmake/idl/python/Dim/RGBTripleArray.py
flatmake/idl/python/Dim/UByteArray.py
flatmake/idl/python/Dim/UInt32bArray.py
flatmake/idl/python/Dim/__init__.py
flatmake/idl/python/flatmake/ColorArray1D.py
flatmake/idl/python/flatmake/Coordinates2D.py
flatmake/idl/python/flatmake/Dim.py
flatmake/idl/python/flatmake/Float32bArray.py
flatmake/idl/python/flatmake/LabeledIndexSet.py
flatmake/idl/python/flatmake/LabeledIndexSuperSet.py
flatmake/idl/python/flatmake/RGBTripleArray.py
flatmake/idl/python/flatmake/UByteArray.py
flatmake/idl/python/flatmake/UInt32bArray.py
flatmake/idl/python/flatmake/__init__.py
flatmake/idl/schema/main.fbs
flatmake/idl/ts/main_generated.ts
flatmake-0.9.6.dist-info/LICENSE
flatmake-0.9.6.dist-info/METADATA
flatmake-0.9.6.dist-info/WHEEL
flatmake-0.9.6.dist-info/entry_points.txt
flatmake-0.9.6.dist-info/top_level.txt
flatmake-0.9.6.dist-info/RECORD
