Metadata-Version: 2.1
Name: flatmake
Version: 0.9.6
Summary: A variety of utilities to build high-level flatbuffers structures
Home-page: https://github.com/dweemx/flatmake
Author: Maxime De Waegeneer
Author-email: mdewaegeneer@gmail.com
License: MIT license
Keywords: flatmake
Platform: UNKNOWN
Classifier: Development Status :: 2 - Pre-Alpha
Classifier: License :: OSI Approved :: MIT License
Classifier: Natural Language :: English
Classifier: Programming Language :: Python :: 3
Requires-Python: >=3.6
Requires-Dist: numpy (>=1.15.4)
Requires-Dist: pandas (>=1.0.3)
Requires-Dist: flatbuffers (==1.12.0)
